odoo/addons/project_task_description_template/README.rst
odoo/addons/project_task_description_template/__init__.py
odoo/addons/project_task_description_template/__manifest__.py
odoo/addons/project_task_description_template/i18n/es.po
odoo/addons/project_task_description_template/i18n/es_MX.po
odoo/addons/project_task_description_template/i18n/it.po
odoo/addons/project_task_description_template/i18n/project_task_description_template.pot
odoo/addons/project_task_description_template/models/__init__.py
odoo/addons/project_task_description_template/models/project_task.py
odoo/addons/project_task_description_template/models/project_task_description_template.py
odoo/addons/project_task_description_template/readme/CONTRIBUTORS.md
odoo/addons/project_task_description_template/readme/DESCRIPTION.md
odoo/addons/project_task_description_template/readme/USAGE.md
odoo/addons/project_task_description_template/security/ir.model.access.csv
odoo/addons/project_task_description_template/security/ir_rule_data.xml
odoo/addons/project_task_description_template/static/description/icon.png
odoo/addons/project_task_description_template/static/description/index.html
odoo/addons/project_task_description_template/tests/__init__.py
odoo/addons/project_task_description_template/tests/test_project_task.py
odoo/addons/project_task_description_template/views/project_task_description_template_view.xml
odoo/addons/project_task_description_template/views/project_task_view.xml
odoo_addon_project_task_description_template-18.0.1.0.0.2.dist-info/METADATA
odoo_addon_project_task_description_template-18.0.1.0.0.2.dist-info/WHEEL
odoo_addon_project_task_description_template-18.0.1.0.0.2.dist-info/top_level.txt
odoo_addon_project_task_description_template-18.0.1.0.0.2.dist-info/RECORD
